AthenaServerClient/__init__.py
AthenaServerClient/_info/__init__.py
AthenaServerClient/_info/_v.py
AthenaServerClient-0.0.0.dist-info/METADATA
AthenaServerClient-0.0.0.dist-info/WHEEL
AthenaServerClient-0.0.0.dist-info/top_level.txt
AthenaServerClient-0.0.0.dist-info/RECORD
